{
  "fetched_at": "2026-05-27T16:05:55.180Z",
  "data": {
    "address": "0xaa9f002000c4f34727e1f0407f363e4ee0be4c27",
    "name": "cardman",
    "tier": "Diamond",
    "tier_v2": 13,
    "badges": 23,
    "streaming": false,
    "portal_link": "https://portal.abs.xyz/profile/0xaa9f002000c4f34727e1f0407f363e4ee0be4c27",
    "total_tx_count": 4358,
    "period_tx_count": 10,
    "period": "14d",
    "top_contracts": [
      {
        "address": "0x3b50de27506f0a8c1f4122a1e6f470009a76ce2a",
        "name": "Abstract Voting",
        "category": "Abstract",
        "is_unknown": false,
        "tx_count": 5,
        "top_method": "0x7060a227"
      },
      {
        "address": "0x34ca1501fae231cc2ebc995ce013dbe882d7d081",
        "name": "Session Key Signing",
        "category": "Abstract",
        "is_unknown": false,
        "tx_count": 3,
        "top_method": "0x5a0694d2"
      },
      {
        "address": "0xb92fe925dc43a0ecde6c8b1a2709c170ec4fff4f",
        "name": "Relay (Contract)",
        "category": "Infra",
        "is_unknown": false,
        "tx_count": 1,
        "top_method": "0xcd6e13f7"
      },
      {
        "address": "0x40018cbb1926dae72dcb315e89aab7320a191d02",
        "name": "Onchain Heroes",
        "category": "Gaming",
        "is_unknown": false,
        "tx_count": 1,
        "top_method": "0x219e0149"
      }
    ]
  }
}