{
  "fetched_at": "2026-05-08T12:45:55.517Z",
  "data": {
    "address": "0x81223fbb85c4c7e2abef9abbc9508dfc97a731b3",
    "name": "Buster",
    "tier": "Diamond",
    "tier_v2": 13,
    "badges": 32,
    "streaming": true,
    "portal_link": "https://portal.abs.xyz/profile/0x81223fbb85c4c7e2abef9abbc9508dfc97a731b3",
    "total_tx_count": 17036,
    "period_tx_count": 9,
    "period": "1d",
    "top_contracts": [
      {
        "address": "0xd9f34cda3667e0b5be4b6fba55d854cfb2ed0694",
        "name": "DEPTH Protocol",
        "category": "DeFi",
        "is_unknown": false,
        "tx_count": 2,
        "top_method": "0x0962ef79"
      },
      {
        "address": "0x84a71ccd554cc1b02749b35d22f684cc8ec987e1",
        "name": "USDC",
        "category": "Others",
        "is_unknown": false,
        "tx_count": 2,
        "top_method": "0xa9059cbb"
      },
      {
        "address": "0xe8142d2f82036b6fc1e79e4ae85cf53fbffdc998",
        "name": "Aborean",
        "category": "DeFi",
        "is_unknown": false,
        "tx_count": 1,
        "top_method": "0xc6b7f1b6"
      },
      {
        "address": "0x34f24235015894fc9543e6e9c4936a17d70fd478",
        "name": "0x34f2...d478",
        "category": "Unknown",
        "is_unknown": true,
        "tx_count": 1,
        "top_method": "0x"
      },
      {
        "address": "0x3b50de27506f0a8c1f4122a1e6f470009a76ce2a",
        "name": "Abstract Voting",
        "category": "Abstract",
        "is_unknown": false,
        "tx_count": 1,
        "top_method": "0x7060a227"
      }
    ]
  }
}