{
  "fetched_at": "2026-04-28T16:32:11.821Z",
  "data": {
    "address": "0x1f7afac6014f37897e4af75c959bea15bce9caf9",
    "name": "BlockCap",
    "tier": "Diamond",
    "tier_v2": 13,
    "badges": 18,
    "streaming": true,
    "portal_link": "https://portal.abs.xyz/profile/0x1f7afac6014f37897e4af75c959bea15bce9caf9",
    "total_tx_count": 5855,
    "period_tx_count": 7,
    "period": "14d",
    "top_contracts": [
      {
        "address": "0x218e6574193e6654a779172bf70dc0fbd149ebf9",
        "name": "0x218e...ebf9",
        "category": "Unknown",
        "is_unknown": true,
        "tx_count": 2,
        "top_method": "0x"
      },
      {
        "address": "0xce2fbf6edfa8b759c4e0c80d73f1aff2a93b054b",
        "name": "0xce2f...054b",
        "category": "Unknown",
        "is_unknown": true,
        "tx_count": 1,
        "top_method": "0xa9059cbb"
      }
    ]
  }
}